streamkompressor/__init__.py
streamkompressor/streamkompressor.py
py_streamkompressor-0.0.2.dist-info/LICENSE
py_streamkompressor-0.0.2.dist-info/METADATA
py_streamkompressor-0.0.2.dist-info/WHEEL
py_streamkompressor-0.0.2.dist-info/top_level.txt
py_streamkompressor-0.0.2.dist-info/RECORD
