Metadata-Version: 2.1
Name: py-streamkompressor
Version: 0.0.2
Summary: IoT Sample Stream Compressor
Home-page: https://github.com/sigsalerno/py-streamkompressor
Author: Dario Salerno
Author-email: info@dariosalerno.com
License: UNKNOWN
Project-URL: Bug Tracker, https://github.com/sigsalerno/py-streamkompressor/issues
Platform: UNKNOWN
Classifier: Programming Language :: Python :: 3
Classifier: License :: OSI Approved :: MIT License
Classifier: Operating System :: OS Independent
Requires-Python: >=3.6
License-File: LICENSE
Requires-Dist: msgpack
